itsolve/fastapi/__init__.py
itsolve/fastapi/abstractions/__init__.py
itsolve/fastapi/abstractions/mixins.py
itsolve/fastapi/abstractions/repository.py
itsolve/fastapi/abstractions/service.py
itsolve/fastapi/abstractions/sql_query.py
itsolve/fastapi/abstractions/uow.py
itsolve/fastapi/abstractions/use_case.py
itsolve/fastapi/core/__init__.py
itsolve/fastapi/core/builders/__init__.py
itsolve/fastapi/core/builders/app/__init__.py
itsolve/fastapi/core/builders/app/application.py
itsolve/fastapi/core/builders/router/__init__.py
itsolve/fastapi/core/builders/router/auth_route.py
itsolve/fastapi/core/builders/router/default_user_payload_schema.py
itsolve/fastapi/core/builders/router/router_builder.py
itsolve/fastapi/core/exceptions.py
itsolve/fastapi/core/responses.py
itsolve/fastapi/integrations/__init__.py
itsolve/fastapi/integrations/casbin/__init__.py
itsolve/fastapi/integrations/casbin/dependencies.py
itsolve/fastapi/integrations/casbin/init_enforcer.py
itsolve/fastapi/integrations/db/__init__.py
itsolve/fastapi/integrations/db/base.py
itsolve/fastapi/integrations/db/column_types.py
itsolve/fastapi/integrations/db/db.py
itsolve/fastapi/integrations/db/mixins/__init__.py
itsolve/fastapi/integrations/db/mixins/id.py
itsolve/fastapi/integrations/db/mixins/timestamp.py
itsolve/fastapi/integrations/logger/__init__.py
itsolve/fastapi/integrations/logger/configuration.py
itsolve/fastapi/integrations/logger/formatter.py
itsolve/fastapi/integrations/logger/README.md
itsolve/fastapi/integrations/observability/__init__.py
itsolve/fastapi/integrations/observability/setting_otlp.py
itsolve/fastapi/integrations/redis.py
itsolve/fastapi/settings/__init__.py
itsolve/fastapi/settings/database_settings.py
itsolve/fastapi/settings/jwt_settings.py
itsolve/fastapi/settings/kafka_settings.py
itsolve/fastapi/settings/logger_settings.py
itsolve/fastapi/settings/observability_settings.py
itsolve/fastapi/settings/permissions_settings.py
itsolve/fastapi/settings/project_settings.py
itsolve-0.15.0.dist-info/METADATA
itsolve-0.15.0.dist-info/WHEEL
itsolve-0.15.0.dist-info/RECORD
