Metadata-Version: 2.3
Name: itsolve
Version: 0.15.0
Summary: 
Author: Roman Bulgakov
Author-email: bulgakovra.w@gmail.com
Requires-Python: >=3.13,<4.0
Classifier: Programming Language :: Python :: 3
Classifier: Programming Language :: Python :: 3.13
Requires-Dist: aiokafka (>=0.12.0,<0.13.0)
Requires-Dist: authx (>=1.4.3,<2.0.0)
Requires-Dist: casbin (>=1.43.0,<2.0.0)
Requires-Dist: fastapi[standard] (>=0.116.1,<0.117.0)
Requires-Dist: loguru (>=0.7.3,<0.8.0)
Requires-Dist: loki-logger-handler (>=1.1.2,<2.0.0)
Requires-Dist: opentelemetry-distro (>=0.57b0,<0.58)
Requires-Dist: opentelemetry-exporter-otlp (>=1.36.0,<2.0.0)
Requires-Dist: opentelemetry-instrumentation-fastapi (>=0.57b0,<0.58)
Requires-Dist: opentelemetry-instrumentation-logging (>=0.57b0,<0.58)
Requires-Dist: pydantic (>=2.11.7,<3.0.0)
Requires-Dist: redis (>=6.3.0,<7.0.0)
Requires-Dist: sqlalchemy[asyncio] (>=2.0.42,<3.0.0)
